html5_parser/stdlib_etree.py
html5_parser/encoding_names.py
html5_parser/__init__.py
html5_parser/soup.py
html5_parser/html_parser.cpython-313-darwin.so
html5_parser/encoding_parser.py
html5_parser/dom.py
rm_html5_parser-0.4.16.dist-info/RECORD
rm_html5_parser-0.4.16.dist-info/WHEEL
rm_html5_parser-0.4.16.dist-info/top_level.txt
rm_html5_parser-0.4.16.dist-info/METADATA
rm_html5_parser-0.4.16.dist-info/licenses/LICENSE
