Metadata-Version: 2.4
Name: rm-html5-parser
Version: 0.4.16
Summary: Fast C based HTML 5 parsing for python, fork of Kovid Goyal html5-parser
Author-email: Kris <kris@rebelmouse.com>
License-Expression: Apache-2.0
Project-URL: Homepage, https://html5-parser.readthedocs.io
Classifier: Development Status :: 5 - Production/Stable
Classifier: Intended Audience :: Developers
Classifier: Natural Language :: English
Classifier: Operating System :: OS Independent
Classifier: Programming Language :: Python
Classifier: Programming Language :: Python :: 3.11
Classifier: Programming Language :: Python :: 3.12
Classifier: Programming Language :: Python :: 3.13
Classifier: Programming Language :: Python :: 3.14
Classifier: Topic :: Text Processing
Classifier: Topic :: Text Processing :: Markup
Classifier: Topic :: Text Processing :: Markup :: HTML
Classifier: Topic :: Text Processing :: Markup :: XML
Requires-Python: >=3.11
License-File: LICENSE
Requires-Dist: chardet
Requires-Dist: lxml>=6.0.2
Provides-Extra: soup
Requires-Dist: beautifulsoup4; extra == "soup"
Dynamic: license-file
